README.rst
setup.py
avbroadcast/__init__.py
avbroadcast/commands.py
avbroadcast/core.py
avbroadcast/hls.py
avbroadcast/util.py
avbroadcast.egg-info/PKG-INFO
avbroadcast.egg-info/SOURCES.txt
avbroadcast.egg-info/dependency_links.txt
avbroadcast.egg-info/entry_points.txt
avbroadcast.egg-info/not-zip-safe
avbroadcast.egg-info/requires.txt
avbroadcast.egg-info/top_level.txt